django_assertmaxnumqueries/__init__.py
django_assertmaxnumqueries-0.1.2.dist-info/DESCRIPTION.rst
django_assertmaxnumqueries-0.1.2.dist-info/METADATA
django_assertmaxnumqueries-0.1.2.dist-info/RECORD
django_assertmaxnumqueries-0.1.2.dist-info/WHEEL
django_assertmaxnumqueries-0.1.2.dist-info/metadata.json
django_assertmaxnumqueries-0.1.2.dist-info/top_level.txt
