Metadata-Version: 2.0
Name: django-assertmaxnumqueries
Version: 0.1.2
Summary: Provides a Django TransactionTestCase.assertMaxNumQueries(),  analogous to the existing TransactionTestCase.assertNumQueries()
Home-page: https://github.com/prismaticd/django_assertmaxnumqueries
Author: Prismatic Digital
Author-email: contact@prismaticdigital.com
License: MIT license
Keywords: django_assertmaxnumqueries
Platform: UNKNOWN
Classifier: Development Status :: 2 - Pre-Alpha
Classifier: Intended Audience :: Developers
Classifier: License :: OSI Approved :: MIT License
Classifier: Natural Language :: English
Classifier: Programming Language :: Python :: 2
Classifier: Programming Language :: Python :: 2.7
Classifier: Programming Language :: Python :: 3
Classifier: Programming Language :: Python :: 3.4
Classifier: Programming Language :: Python :: 3.5
Classifier: Programming Language :: Python :: 3.6
